bizcal/__init__.py
bizcal-0.3.0.dist-info/licenses/LICENSE
bizcal-0.3.0.dist-info/METADATA
bizcal-0.3.0.dist-info/WHEEL
bizcal-0.3.0.dist-info/top_level.txt
bizcal-0.3.0.dist-info/RECORD
