Metadata-Version: 2.4
Name: bizcal
Version: 0.3.0
Summary: Pythonic Business (Trading) Calendar.
Author-email: Sun Yijiang <sunyijiang@gmail.com>
License-Expression: MIT
Project-URL: Homepage, https://github.com/sunyj/bizcal
Project-URL: Bug Tracker, https://github.com/sunyj/bizcal/issues
Classifier: Programming Language :: Python :: 3
Classifier: Operating System :: OS Independent
Requires-Python: >=3.6
License-File: LICENSE
Dynamic: license-file
